yieldfixture/__init__.py
yieldfixture-0.3.2.dist-info/DESCRIPTION.rst
yieldfixture-0.3.2.dist-info/entry_points.txt
yieldfixture-0.3.2.dist-info/METADATA
yieldfixture-0.3.2.dist-info/metadata.json
yieldfixture-0.3.2.dist-info/RECORD
yieldfixture-0.3.2.dist-info/top_level.txt
yieldfixture-0.3.2.dist-info/WHEEL
