Metadata-Version: 2.0
Name: yieldfixture
Version: 0.3.2
Summary: tiny yield fixture
Home-page: https://github.com/podhmo/yieldfixture
Author: podhmo
Author-email: ababjam61+github@gmail.com
License: UNKNOWN
Platform: UNKNOWN
Classifier: Programming Language :: Python
Classifier: Programming Language :: Python :: Implementation :: CPython
Provides-Extra: docs
Provides-Extra: testing
